LICENSE
MANIFEST.in
README.rst
setup.py
django_sm8_jobs.egg-info/PKG-INFO
django_sm8_jobs.egg-info/SOURCES.txt
django_sm8_jobs.egg-info/dependency_links.txt
django_sm8_jobs.egg-info/requires.txt
django_sm8_jobs.egg-info/top_level.txt
jobs/__init__.py
jobs/admin.py
jobs/apps.py
jobs/forms.py
jobs/models.py
jobs/tests.py
jobs/urls.py
jobs/views.py
jobs/migrations/0001_initial.py
jobs/migrations/__init__.py
jobs/static/.DS_Store
jobs/static/human.txt
jobs/static/jobs/.DS_Store
jobs/static/jobs/css/.DS_Store
jobs/static/jobs/css/bootstrap-theme.css
jobs/static/jobs/css/bootstrap-theme.css.map
jobs/static/jobs/css/bootstrap-theme.min.css
jobs/static/jobs/css/bootstrap-theme.min.css.map
jobs/static/jobs/css/bootstrap.css
jobs/static/jobs/css/bootstrap.css.map
jobs/static/jobs/css/bootstrap.min.css
jobs/static/jobs/css/bootstrap.min.css.map
jobs/static/jobs/css/style.css
jobs/static/jobs/fonts/glyphicons-halflings-regular.eot
jobs/static/jobs/fonts/glyphicons-halflings-regular.svg
jobs/static/jobs/fonts/glyphicons-halflings-regular.ttf
jobs/static/jobs/fonts/glyphicons-halflings-regular.woff
jobs/static/jobs/fonts/glyphicons-halflings-regular.woff2
jobs/static/jobs/js/bootstrap.js
jobs/static/jobs/js/bootstrap.min.js
jobs/static/jobs/js/npm.js
jobs/templates/.DS_Store
jobs/templates/jobs/attachments.html
jobs/templates/jobs/base.html
jobs/templates/jobs/create_user.html
jobs/templates/jobs/details.html
jobs/templates/jobs/index.html
jobs/templates/jobs/login.html
jobs/templates/jobs/notes.html
jobs/templates/jobs/profile.html
jobs/templates/jobs/submit.html